hybridcache/__init__.py
hybridcache/cache.py
hybridcache-0.1.0.dist-info/licenses/LICENSE
hybridcache-0.1.0.dist-info/METADATA
hybridcache-0.1.0.dist-info/WHEEL
hybridcache-0.1.0.dist-info/top_level.txt
hybridcache-0.1.0.dist-info/RECORD
